[
  {
    "functionLabel": "",
    "functionName": "cpyData_copro",
    "id": 0,
    "ifcond": "",
    "insert_position": "",
    "label": "",
    "pragma": {
      "name": "TOP",
      "option": [
        {
          "name": "name",
          "value": "cpyData_copro"
        }
      ]
    },
    "slx": false,
    "sourceFile": "D:/ITCL_video/movDataZynq/prj_hls/cpy_Data/solution1/directives.tcl",
    "sourceLine": 7,
    "success": true
  },
  {
    "functionLabel": "",
    "functionName": "cpyData_copro",
    "id": 1,
    "ifcond": "",
    "insert_position": "",
    "label": "",
    "pragma": {
      "name": "TOP",
      "option": [
        {
          "name": "name",
          "value": "cpyData_copro"
        }
      ]
    },
    "slx": false,
    "sourceFile": "D:/ITCL_video/movDataZynq/prj_hls/cpy_Data/solution1/csynth.tcl",
    "sourceLine": 16,
    "success": true
  }
]